Workbook
Name NativeTimeline_Date: #N/A

Sheet Dashboard
A13: Date | B13: No. Of Rides | C13: Total KM. | D13: Total Hrs. | E13: Total Order Amount | F13: Tax | G13: Total Earning | H13: Incentive(s) | I13: Total Fuel Cost | J13: Recharge Amount | K13: Day's Net Earning
A14: 46149 | B14: 15 | C14: 68.67 | D14: 0.24444444 | E14: 647 | F14: 64.53 | G14: 582.47 | I14: 132.05769 | J14: 399 | K14: 51.412308
A15: 46150 | B15: 15 | C15: 81.03 | D15: 0.22916667 | E15: 768 | F15: 68.19 | G15: 699.81 | I15: 155.82692 | K15: 543.98308
A16: 46151 | B16: 9 | C16: 40.41 | D16: 0.1875 | E16: 386 | F16: 38.6 | G16: 347.4 | I16: 77.711538 | K16: 275.68846
A17: Grand Total | B17: 39 | C17: 190.11 | D17: 0.66111111 | E17: 1801 | F17: 171.32 | G17: 1629.68 | I17: 365.59615 | J17: 399 | K17: 871.08385

Sheet Ride_Entries
A1: Ride Data
A3: S.No. | B3: Date | C3: Order ID | D3: Pickup KM | E3: Drop KM | F3: Total KM | G3: Order Amount | H3: Tax Deducted | I3: Earning | J3: Payment Type
A4: =IF($B$4=" ", " ", ROW()-3) -> 1 | B4: 46149 | C4: XXXXX81521969049002 | D4: 1.38 | E4: 1.67 | F4: =SUM(Table1[[#This Row],[Pickup KM]:[Drop KM]]) -> 3.05 | G4: 26 | H4: 3.49 | I4: =G4-H4 -> 22.51 | J4: Online
A5: =IF($B$4=" ", " ", ROW()-3) -> 2 | B5: 46149 | C5: XXXXX81533881775107 | D5: 1.39 | E5: 4.14 | F5: =SUM(Table1[[#This Row],[Pickup KM]:[Drop KM]]) -> 5.53 | G5: 43 | H5: 4.3 | I5: =G5-H5 -> 38.7 | J5: Online
A6: =IF($B$4=" ", " ", ROW()-3) -> 3 | B6: 46149 | C6: XXXXX81549890627238 | D6: 2.15 | E6: 4.77 | F6: =SUM(Table1[[#This Row],[Pickup KM]:[Drop KM]]) -> 6.92 | G6: 48 | H6: 4.53 | I6: =G6-H6 -> 43.47 | J6: Online
A7: =IF($B$4=" ", " ", ROW()-3) -> 4 | B7: 46149 | C7: XXXXX81565818236687 | D7: 0.64 | E7: 1.82 | F7: =SUM(Table1[[#This Row],[Pickup KM]:[Drop KM]]) -> 2.46 | G7: 41 | H7: 4.2 | I7: =G7-H7 -> 36.8 | J7: Online
A8: =IF($B$4=" ", " ", ROW()-3) -> 5 | B8: 46149 | C8: XXXXX81578136147919 | D8: 1.65 | E8: 3.73 | F8: =SUM(Table1[[#This Row],[Pickup KM]:[Drop KM]]) -> 5.38 | G8: 40 | H8: 4.15 | I8: =G8-H8 -> 35.85 | J8: Online
A9: =IF($B$4=" ", " ", ROW()-3) -> 6 | B9: 46149 | C9: XXXXX81592305898788 | D9: 1.33 | E9: 3.83 | F9: =SUM(Table1[[#This Row],[Pickup KM]:[Drop KM]]) -> 5.16 | G9: 47 | H9: 4.49 | I9: =G9-H9 -> 42.51 | J9: Online
A10: =IF($B$4=" ", " ", ROW()-3) -> 7 | B10: 46149 | C10: XXXXX81605635127782 | D10: 1.19 | E10: 8.53 | F10: =SUM(Table1[[#This Row],[Pickup KM]:[Drop KM]]) -> 9.72 | G10: 95 | H10: 6.77 | I10: =G10-H10 -> 88.23 | J10: Online
A11: =IF($B$4=" ", " ", ROW()-3) -> 8 | B11: 46149 | C11: XXXXX81633738961501 | D11: 0.01 | E11: 2.96 | F11: =SUM(Table1[[#This Row],[Pickup KM]:[Drop KM]]) -> 2.97 | G11: 34 | H11: 3.87 | I11: =G11-H11 -> 30.13 | J11: Online
A12: =IF($B$4=" ", " ", ROW()-3) -> 9 | B12: 46149 | C12: XXXXX81643770964544 | D12: 1.28 | E12: 2.72 | F12: =SUM(Table1[[#This Row],[Pickup KM]:[Drop KM]]) -> 4 | G12: 38 | H12: 4.06 | I12: =G12-H12 -> 33.94 | J12: Online
A13: =IF($B$4=" ", " ", ROW()-3) -> 10 | B13: 46149 | C13: XXXXX81654635073945 | D13: 0.09 | E13: 1.66 | F13: =SUM(Table1[[#This Row],[Pickup KM]:[Drop KM]]) -> 1.75 | G13: 33 | H13: 3.82 | I13: =G13-H13 -> 29.18 | J13: Online
A14: =IF($B$4=" ", " ", ROW()-3) -> 11 | B14: 46149 | C14: XXXXX81663731662698 | D14: 0.95 | E14: 2.93 | F14: =SUM(Table1[[#This Row],[Pickup KM]:[Drop KM]]) -> 3.88 | G14: 31 | H14: 3.72 | I14: =G14-H14 -> 27.28 | J14: Online
A15: =IF($B$4=" ", " ", ROW()-3) -> 12 | B15: 46149 | C15: XXXXX81679657254032 | D15: 0 | E15: 2.46 | F15: =SUM(Table1[[#This Row],[Pickup KM]:[Drop KM]]) -> 2.46 | G15: 27 | H15: 3.53 | I15: =G15-H15 -> 23.47 | J15: Online
... A100: =IF($B$4=" ", " ", ROW()-3) -> 97 | B100: 46160 | C100: XXXXX91227010979141 | D100: 1.51 | E100: 5.34 | F100: =SUM(Table1[[#This Row],[Pickup KM]:[Drop KM]]) -> 6.85 | G100: 67 | H100: 5.44 | I100: =G100-H100 -> 61.56 | J100: Online

Sheet Daily_Summary
A1: Daily Dashboard
A3: Date | B3: Start Time | C3: End Time | D3: Total Hours | E3: Rides | F3: Total KM | G3: Order Amount | H3: Tax Deducted | I3: Earning | J3: Wallet | K3: Cash | L3: Cancellation Fees | M3: Incentive | N3: Fuel Cost | O3: Recharge | P3: Net Earning | Q3: Transferred To A/C
A4: 46149 | B4: 0.68472222 | C4: 0.92916667 | D4: =C4-B4 -> 0.24444444 | E4: =COUNTIF(Ride_Entries!B:B, Table2[[#This Row],[Date]]) -> 15 | F4: =SUMIF(Ride_Entries!B:B, Table2[[#This Row],[Date]], Ride_Entries!F:F) -> 68.67 | G4: =SUMIF(Ride_Entries!B:B, Table2[[#This Row],[Date]], Ride_Entries!G:G) -> 647 | H4: =SUMIF(Ride_Entries!B:B, Table2[[#This Row],[Date]], Ride_Entries!H:H) -> 64.53 | I4: =Table2[[#This Row],[Order Amount]]-Table2[[#This Row],[Tax Deducted]] -> 582.47 | J4: =SUMIFS(Ride_Entries!I:I, Ride_Entries!B:B, Table2[[#This Row],[Date]], Ride_Entries!J:J, "Online") -> 582.47 | K4: =SUMIFS(Ride_Entries!I:I, Ride_Entries!B:B, Table2[[#This Row],[Date]], Ride_Entries!J:J, "Cash") -> 0 | N4: =(F4/52)*100 -> 132.05769 | O4: 399 | P4: =((Table2[[#This Row],[Earning]]+Table2[[#This Row],[Cancellation Fees]]+Table2[[#This Row],[Incentive]])-(Table2[[#This Row],[Fuel Cost]]+Table2[[#This Row],[Recharge]])) -> 51.412308
A5: 46150 | B5: 0.70833333 | C5: 0.9375 | D5: =C5-B5 -> 0.22916667 | E5: =COUNTIF(Ride_Entries!B:B, Table2[[#This Row],[Date]]) -> 15 | F5: =SUMIF(Ride_Entries!B:B, Table2[[#This Row],[Date]], Ride_Entries!F:F) -> 81.03 | G5: =SUMIF(Ride_Entries!B:B, Table2[[#This Row],[Date]], Ride_Entries!G:G) -> 768 | H5: =SUMIF(Ride_Entries!B:B, Table2[[#This Row],[Date]], Ride_Entries!H:H) -> 68.19 | I5: =Table2[[#This Row],[Order Amount]]-Table2[[#This Row],[Tax Deducted]] -> 699.81 | J5: =SUMIFS(Ride_Entries!I:I, Ride_Entries!B:B, Table2[[#This Row],[Date]], Ride_Entries!J:J, "Online") -> 603.77 | K5: =SUMIFS(Ride_Entries!I:I, Ride_Entries!B:B, Table2[[#This Row],[Date]], Ride_Entries!J:J, "Cash") -> 96.04 | N5: =(F5/52)*100 -> 155.82692 | P5: =((Table2[[#This Row],[Earning]]+Table2[[#This Row],[Cancellation Fees]]+Table2[[#This Row],[Incentive]])-(Table2[[#This Row],[Fuel Cost]]+Table2[[#This Row],[Recharge]])) -> 543.98308
A6: 46151 | B6: 0.70833333 | C6: 0.89583333 | D6: =C6-B6 -> 0.1875 | E6: =COUNTIF(Ride_Entries!B:B, Table2[[#This Row],[Date]]) -> 9 | F6: =SUMIF(Ride_Entries!B:B, Table2[[#This Row],[Date]], Ride_Entries!F:F) -> 40.41 | G6: =SUMIF(Ride_Entries!B:B, Table2[[#This Row],[Date]], Ride_Entries!G:G) -> 386 | H6: =SUMIF(Ride_Entries!B:B, Table2[[#This Row],[Date]], Ride_Entries!H:H) -> 38.6 | I6: =Table2[[#This Row],[Order Amount]]-Table2[[#This Row],[Tax Deducted]] -> 347.4 | J6: =SUMIFS(Ride_Entries!I:I, Ride_Entries!B:B, Table2[[#This Row],[Date]], Ride_Entries!J:J, "Online") -> 288.08 | K6: =SUMIFS(Ride_Entries!I:I, Ride_Entries!B:B, Table2[[#This Row],[Date]], Ride_Entries!J:J, "Cash") -> 59.32 | L6: 6 | N6: =(F6/52)*100 -> 77.711538 | P6: =((Table2[[#This Row],[Earning]]+Table2[[#This Row],[Cancellation Fees]]+Table2[[#This Row],[Incentive]])-(Table2[[#This Row],[Fuel Cost]]+Table2[[#This Row],[Recharge]])) -> 275.68846 | Q6: 1476
A7: 46153 | B7: 0.66666667 | C7: 0.91666667 | D7: =C7-B7 -> 0.25 | E7: =COUNTIF(Ride_Entries!B:B, Table2[[#This Row],[Date]]) -> 12 | F7: =SUMIF(Ride_Entries!B:B, Table2[[#This Row],[Date]], Ride_Entries!F:F) -> 84.72 | G7: =SUMIF(Ride_Entries!B:B, Table2[[#This Row],[Date]], Ride_Entries!G:G) -> 883 | H7: =SUMIF(Ride_Entries!B:B, Table2[[#This Row],[Date]], Ride_Entries!H:H) -> 69.02 | I7: =Table2[[#This Row],[Order Amount]]-Table2[[#This Row],[Tax Deducted]] -> 813.98 | J7: =SUMIFS(Ride_Entries!I:I, Ride_Entries!B:B, Table2[[#This Row],[Date]], Ride_Entries!J:J, "Online") -> 557.26 | K7: =SUMIFS(Ride_Entries!I:I, Ride_Entries!B:B, Table2[[#This Row],[Date]], Ride_Entries!J:J, "Cash") -> 256.72 | L7: 9 | N7: =(F7/52)*100 -> 162.92308 | P7: =((Table2[[#This Row],[Earning]]+Table2[[#This Row],[Cancellation Fees]]+Table2[[#This Row],[Incentive]])-(Table2[[#This Row],[Fuel Cost]]+Table2[[#This Row],[Recharge]])) -> 660.05692
A8: 46154 | D8: =C8-B8 -> 0 | E8: =COUNTIF(Ride_Entries!B:B, Table2[[#This Row],[Date]]) -> 0 | F8: =SUMIF(Ride_Entries!B:B, Table2[[#This Row],[Date]], Ride_Entries!F:F) -> 0 | G8: =SUMIF(Ride_Entries!B:B, Table2[[#This Row],[Date]], Ride_Entries!G:G) -> 0 | H8: =SUMIF(Ride_Entries!B:B, Table2[[#This Row],[Date]], Ride_Entries!H:H) -> 0 | I8: =Table2[[#This Row],[Order Amount]]-Table2[[#This Row],[Tax Deducted]] -> 0 | J8: =SUMIFS(Ride_Entries!I:I, Ride_Entries!B:B, Table2[[#This Row],[Date]], Ride_Entries!J:J, "Online") -> 0 | K8: =SUMIFS(Ride_Entries!I:I, Ride_Entries!B:B, Table2[[#This Row],[Date]], Ride_Entries!J:J, "Cash") -> 0 | N8: =(F8/52)*100 -> 0 | P8: =((Table2[[#This Row],[Earning]]+Table2[[#This Row],[Cancellation Fees]]+Table2[[#This Row],[Incentive]])-(Table2[[#This Row],[Fuel Cost]]+Table2[[#This Row],[Recharge]])) -> 0 | Q8: 544
A9: 46156 | B9: 0.36458333 | C9: 0.65625 | D9: =C9-B9 -> 0.29166667 | E9: =COUNTIF(Ride_Entries!B:B, Table2[[#This Row],[Date]]) -> 14 | F9: =SUMIF(Ride_Entries!B:B, Table2[[#This Row],[Date]], Ride_Entries!F:F) -> 111.72 | G9: =SUMIF(Ride_Entries!B:B, Table2[[#This Row],[Date]], Ride_Entries!G:G) -> 1043 | H9: =SUMIF(Ride_Entries!B:B, Table2[[#This Row],[Date]], Ride_Entries!H:H) -> 75.11 | I9: =Table2[[#This Row],[Order Amount]]-Table2[[#This Row],[Tax Deducted]] -> 967.89 | J9: =SUMIFS(Ride_Entries!I:I, Ride_Entries!B:B, Table2[[#This Row],[Date]], Ride_Entries!J:J, "Online") -> 659.35 | K9: =SUMIFS(Ride_Entries!I:I, Ride_Entries!B:B, Table2[[#This Row],[Date]], Ride_Entries!J:J, "Cash") -> 308.54 | L9: 6 | M9: 100 | N9: =(F9/52)*100 -> 214.84615 | P9: =((Table2[[#This Row],[Earning]]+Table2[[#This Row],[Cancellation Fees]]+Table2[[#This Row],[Incentive]])-(Table2[[#This Row],[Fuel Cost]]+Table2[[#This Row],[Recharge]])) -> 859.04385 | Q9: 760
A10: 46159 | B10: 0.65972222 | C10: 0.91666667 | D10: =C10-B10 -> 0.25694444 | E10: =COUNTIF(Ride_Entries!B:B, Table2[[#This Row],[Date]]) -> 18 | F10: =SUMIF(Ride_Entries!B:B, Table2[[#This Row],[Date]], Ride_Entries!F:F) -> 93.12 | G10: =SUMIF(Ride_Entries!B:B, Table2[[#This Row],[Date]], Ride_Entries!G:G) -> 858 | H10: =SUMIF(Ride_Entries!B:B, Table2[[#This Row],[Date]], Ride_Entries!H:H) -> 81.36 | I10: =Table2[[#This Row],[Order Amount]]-Table2[[#This Row],[Tax Deducted]] -> 776.64 | J10: =SUMIFS(Ride_Entries!I:I, Ride_Entries!B:B, Table2[[#This Row],[Date]], Ride_Entries!J:J, "Online") -> 449.87 | K10: =SUMIFS(Ride_Entries!I:I, Ride_Entries!B:B, Table2[[#This Row],[Date]], Ride_Entries!J:J, "Cash") -> 326.77 | M10: 100 | N10: =(F10/52)*100 -> 179.07692 | O10: 219 | P10: =((Table2[[#This Row],[Earning]]+Table2[[#This Row],[Cancellation Fees]]+Table2[[#This Row],[Incentive]])-(Table2[[#This Row],[Fuel Cost]]+Table2[[#This Row],[Recharge]])) -> 478.56308
A11: 46160 | B11: 0.67708333 | C11: 0.94791667 | D11: =C11-B11 -> 0.27083333 | E11: =COUNTIF(Ride_Entries!B:B, Table2[[#This Row],[Date]]) -> 14 | F11: =SUMIF(Ride_Entries!B:B, Table2[[#This Row],[Date]], Ride_Entries!F:F) -> 92.57 | G11: =SUMIF(Ride_Entries!B:B, Table2[[#This Row],[Date]], Ride_Entries!G:G) -> 785 | H11: =SUMIF(Ride_Entries!B:B, Table2[[#This Row],[Date]], Ride_Entries!H:H) -> 68.77 | I11: =Table2[[#This Row],[Order Amount]]-Table2[[#This Row],[Tax Deducted]] -> 716.23 | J11: =SUMIFS(Ride_Entries!I:I, Ride_Entries!B:B, Table2[[#This Row],[Date]], Ride_Entries!J:J, "Online") -> 540.97 | K11: =SUMIFS(Ride_Entries!I:I, Ride_Entries!B:B, Table2[[#This Row],[Date]], Ride_Entries!J:J, "Cash") -> 175.26 | N11: =(F11/52)*100 -> 178.01923 | P11: =((Table2[[#This Row],[Earning]]+Table2[[#This Row],[Cancellation Fees]]+Table2[[#This Row],[Incentive]])-(Table2[[#This Row],[Fuel Cost]]+Table2[[#This Row],[Recharge]])) -> 538.21077 | Q11: 514.69
A12: 46161 | D12: =C12-B12 -> 0 | E12: =COUNTIF(Ride_Entries!B:B, Table2[[#This Row],[Date]]) -> 0 | F12: =SUMIF(Ride_Entries!B:B, Table2[[#This Row],[Date]], Ride_Entries!F:F) -> 0 | G12: =SUMIF(Ride_Entries!B:B, Table2[[#This Row],[Date]], Ride_Entries!G:G) -> 0 | H12: =SUMIF(Ride_Entries!B:B, Table2[[#This Row],[Date]], Ride_Entries!H:H) -> 0 | I12: =Table2[[#This Row],[Order Amount]]-Table2[[#This Row],[Tax Deducted]] -> 0 | J12: =SUMIFS(Ride_Entries!I:I, Ride_Entries!B:B, Table2[[#This Row],[Date]], Ride_Entries!J:J, "Online") -> 0 | K12: =SUMIFS(Ride_Entries!I:I, Ride_Entries!B:B, Table2[[#This Row],[Date]], Ride_Entries!J:J, "Cash") -> 0 | N12: =(F12/52)*100 -> 0 | P12: =((Table2[[#This Row],[Earning]]+Table2[[#This Row],[Cancellation Fees]]+Table2[[#This Row],[Incentive]])-(Table2[[#This Row],[Fuel Cost]]+Table2[[#This Row],[Recharge]])) -> 0 | Q12: 510

Sheet Pivots
A11: Row Labels | B11: Sum of Rides | C11: Sum of Total KM | D11: Sum of Total Hours | E11: Sum of Order Amount | F11: Sum of Tax Deducted | G11: Sum of Earning | H11: Sum of Incentive | I11: Sum of Fuel Cost | J11: Sum of Recharge | K11: Sum of Net Earning
A12: 46149 | B12: 15 | C12: 68.67 | D12: 0.24444444 | E12: 647 | F12: 64.53 | G12: 582.47 | I12: 132.05769 | J12: 399 | K12: 51.412308
A13: 46150 | B13: 15 | C13: 81.03 | D13: 0.22916667 | E13: 768 | F13: 68.19 | G13: 699.81 | I13: 155.82692 | K13: 543.98308
A14: 46151 | B14: 9 | C14: 40.41 | D14: 0.1875 | E14: 386 | F14: 38.6 | G14: 347.4 | I14: 77.711538 | K14: 275.68846
A15: Grand Total | B15: 39 | C15: 190.11 | D15: 0.66111111 | E15: 1801 | F15: 171.32 | G15: 1629.68 | I15: 365.59615 | J15: 399 | K15: 871.08385
